{"ocr_results":[{"text":" 文年 上 御筆沉浮缝","box":[[258,89],[560,96],[559,134],[257,128]]},{"text":"「梁效了住事","box":[[332,139],[474,142],[474,170],[332,167]]},{"text":"乳膠廠動期間，我抽空去看望在北京木材公司工作的朋","box":[[132,293],[697,294],[697,314],[132,313]]},{"text":"友，他在辨公室問我：「群犯錯了，你知道？」當","box":[[131,331],[696,333],[696,354],[131,351]]},{"text":"時，由於辦公室的人很多，我没有答話，岔開去别的了。","box":[[132,374],[691,374],[691,391],[132,391]]},{"text":"厂梁效！那位頭頭又很快獲悉，找我話，他：「你岔","box":[[135,413],[694,413],[694,430],[135,430]]},{"text":"了，等於默猩群犯了錯。」","box":[[134,452],[430,452],[430,469],[134,469]]},{"text":"後來，李家寬和王世敏也經歷了一次信任危機·大約在","box":[[175,490],[696,488],[696,509],[175,510]]},{"text":"一九七六年四、五月間，宋柏年召開北大、清華大批判組全","box":[[132,529],[695,529],[695,549],[132,549]]},{"text":"體成員大會，對李家寬、王世敏雨人的工作作風進行揭發、","box":[[132,568],[691,567],[691,585],[132,586]]},{"text":"批判。猩群、謝静宜也参加了此會亚支持大家對李、王二人","box":[[132,606],[694,605],[694,625],[132,626]]},{"text":"的批判，要求他們立即離開大批判組，回原單位工作。那","box":[[131,646],[696,646],[696,666],[131,666]]},{"text":"天，我正好回家，没有参加那個批判會·事後，有的同志向","box":[[130,685],[694,684],[694,704],[130,705]]},{"text":"我簡要介绍了會情况。李、王二人調離後，宋柏年携任","box":[[132,724],[694,723],[694,743],[132,744]]},{"text":"「梁效」主要負人，紅衛兵出身的郁龍餘和中文系的孫静","box":[[132,764],[692,763],[692,782],[132,783]]},{"text":"進入導班子·北大委書記、原八三四一部除副政委王連","box":[[130,803],[695,802],[695,822],[130,823]]},{"text":"龍和北大黛委常委魏銀秋得知此事後，處理欠安，強調","box":[[131,842],[695,841],[695,861],[131,862]]},{"text":"即使李、王二人工作作風或其他方面存在許多缺點，但政治","box":[[130,881],[694,879],[694,899],[130,901]]},{"text":"上没有什应大問題，不應調離「梁效」。猩、謝考虑了王連","box":[[130,920],[697,919],[697,940],[130,941]]},{"text":"龍和魏銀秋的意見，兩、三天後，文将李家寬和王世敏調回","box":[[132,959],[693,957],[693,976],[132,978]]},{"text":"大批判組官復原職。","box":[[132,998],[342,998],[342,1018],[132,1018]]},{"text":"於上述種種原因，我向「梁效』導打了報告，要求","box":[[174,1037],[693,1034],[693,1055],[174,1058]]},{"text":"I.30","box":[[399,1145],[432,1145],[432,1164],[399,1164]]}],"dimensions":{"height":1257,"width":817}}