{"ocr_results":[{"text":"马克思、恩格斯、列宁、鲁迅都在后来批判过去。","box":[[253,251],[1558,194],[1562,269],[257,325]]},{"text":"2、攻击、低毁伟大领袖毛主席和光辉的","box":[[2562,273],[3799,293],[3798,360],[2561,339]]},{"text":"一张春桥一九六六年一月二十日的一次谈话（徐景贤记录）","box":[[705,367],[1859,309],[1862,363],[707,421]]},{"text":"毛泽东思想","box":[[2410,404],[2754,409],[2753,477],[2409,471]]},{"text":"看了马克思的原稿那你就知道了，每一篇稿子不知改了多","box":[[378,532],[1926,471],[1929,544],[381,605]]},{"text":"《论十大关系》完全是苏联的一套，无非是企业管理、物","box":[[2405,584],[3937,604],[3936,667],[2404,647]]},{"text":"少遍，………．“无产阶级”这样一个名词，马克思、恩格斯最后","box":[[252,658],[1930,602],[1932,681],[255,737]]},{"text":"质刺激。","box":[[2261,703],[2472,707],[2470,777],[2259,773]]},{"text":"下这样一个比较正确的名词，是花了二十年的时间呀！我们的","box":[[262,787],[1932,734],[1934,807],[264,860]]},{"text":"一张春桥一九六九年的话，王知常揭发交代","box":[[2665,841],[3565,853],[3564,902],[2665,890]]},{"text":"两个老祖宗，为无产阶级创造理论，非常艰苦，花几十年才下","box":[[262,916],[1930,870],[1932,938],[264,984]]},{"text":"主席的诗，也不是句句精采嘛，精采的就这么几句。","box":[[2390,961],[3770,978],[3769,1040],[2389,1023]]},{"text":"这样比较正确的名词，这都是档案里看出来的。","box":[[262,1040],[1519,1014],[1520,1080],[263,1106]]},{"text":"—张春桥一九六九年夏与《海港》剧组编剧人员讨论剧本时的","box":[[2655,1094],[3935,1106],[3935,1150],[2655,1139]]},{"text":"张春桥一九六九年六月二十八日在上海整党建党三个试点单","box":[[720,1161],[1936,1135],[1937,1185],[721,1210]]},{"text":"讲话","box":[[2719,1165],[2823,1169],[2821,1224],[2717,1219]]},{"text":"麻基创","box":[[364,1182],[691,1182],[691,1270],[364,1270]]},{"text":"位座谈会上讲话","box":[[732,1242],[1048,1238],[1049,1284],[732,1288]]},{"text":"我最近也在重读（《毛选》），越读越感到自己对今天各","box":[[2385,1312],[3934,1326],[3933,1386],[2384,1372]]},{"text":"列宁搞了个工农检察院，选了好多工农参加中央工作，结","box":[[395,1419],[1938,1400],[1938,1461],[396,1480]]},{"text":"阶级的情况，真是不甚了了，越是觉得应当弄清楚。","box":[[2262,1437],[3637,1450],[3636,1510],[2261,1496]]},{"text":"果不解决问题，变修了。二百多个中央委员能解决问题吗？","box":[[274,1549],[1839,1536],[1840,1592],[274,1606]]},{"text":"张春桥一九七六年六月十二日在朱永嘉信上的批语","box":[[2718,1567],[3747,1576],[3746,1621],[2717,1612]]},{"text":"张春桥一九七六年四月底同女儿张维维的谈话","box":[[729,1670],[1652,1665],[1653,1710],[729,1715]]},{"text":"我们党搞民主主义，搞了二十八年，许多问题认识不清","box":[[2380,1691],[3932,1703],[3932,1765],[2379,1753]]},{"text":"楚，等认识清楚了，已解放了。社会主义，你看，又快二十八","box":[[2255,1816],[3930,1831],[3930,1892],[2255,1877]]},{"text":"不批修，政治经济学写不好。要知道，斯大林错误的东西","box":[[399,1827],[1940,1824],[1940,1885],[399,1889]]},{"text":"年了，付出的代价不少吧。许多同志的思想还停留在民主革命","box":[[2249,1938],[3929,1953],[3928,2020],[2248,2004]]},{"text":"影响还是不小的。我们的政治经济学，应当帮助干部从修正主","box":[[277,1951],[1941,1953],[1941,2016],[277,2014]]},{"text":"义的影响、从资产阶级的影响下解放出来，从民主革命进到社","box":[[278,2075],[1950,2084],[1949,2150],[277,2142]]},{"text":"时期···革资产阶级的命，对象在那里？还是《二十三条》、","box":[[2247,2066],[3889,2077],[3889,2144],[2246,2132]]},{"text":"《十六条》中讲的，关键在党内，特别是在高级领导机关，在","box":[[2255,2193],[3925,2203],[3925,2269],[2255,2259]]},{"text":"会主义革命。","box":[[281,2206],[606,2206],[606,2269],[281,2269]]},{"text":"张春桥在朱永嘉一九七五年十二月三十一日信上的批语","box":[[738,2325],[1858,2347],[1857,2399],[737,2377]]},{"text":"中央。","box":[[2233,2319],[2399,2319],[2399,2393],[2233,2393]]},{"text":"张春桥的话，一九七六年一月二十九日黄涛在上海市委常委","box":[[2703,2445],[3924,2455],[3923,2506],[2703,2496]]},{"text":"当时艰苦得很，恩格斯只好跑到他父亲的工厂去。他父亲","box":[[410,2486],[1953,2515],[1952,2587],[408,2558]]},{"text":"会上传达","box":[[2706,2524],[2895,2524],[2895,2575],[2706,2575]]},{"text":"是资本家，不是红五类。列宁还不是这样？毛主席也是这样…····","box":[[278,2608],[1940,2642],[1939,2720],[277,2686]]},{"text":"总根子是辫帅这一点似乎还可以考虑。辫子党的头子应是","box":[[2372,2628],[3921,2640],[3920,2713],[2371,2701]]},{"text":"张春桥一九六六年十月七日接见部分福建赴京学生时的讲话","box":[[735,2742],[1960,2776],[1958,2837],[733,2803]]},{"text":"那个被废除了的皇帝吧？应是整个制度吧？不过不要再写文章","box":[[2240,2756],[3924,2771],[3923,2839],[2240,2824]]},{"text":"-3—","box":[[3627,2891],[3816,2899],[3814,2957],[3624,2949]]},{"text":"-2-","box":[[391,2903],[578,2903],[578,2956],[391,2956]]}],"dimensions":{"height":3072,"width":4096}}