{"ocr_results":[{"text":"826","box":[[131,116],[162,116],[162,137],[131,137]]},{"text":"周恩来传","box":[[426,116],[499,116],[499,134],[426,134]]},{"text":"他说：现在我们正处于从根本上打倒国民党走向完全打倒国","box":[[163,171],[812,171],[812,191],[163,191]]},{"text":"民党的过渡时期，正在由分散到统一。这不是几个月而是要几年","box":[[114,210],[812,210],[812,228],[114,228]]},{"text":"才能走完的。过渡时期是特点，我们要抓住这一特点，不然会犯","box":[[112,247],[811,247],[811,267],[112,267]]},{"text":"错误。由于地区的不平衡，因而又产生了区域性的问题，分权的","box":[[112,284],[811,284],[811,304],[112,304]]},{"text":"问题。中国不是联邦，但是带区域性的。这么大的中国，如果过","box":[[112,322],[813,322],[813,342],[112,342]]},{"text":"分强调集中，会办不好事。所以在组织形式上不能一下子都集","box":[[113,361],[811,361],[811,378],[113,378]]},{"text":"权，一定要授权地方，才能发挥积极性。但中央必须成为掌握政","box":[[112,397],[812,397],[812,417],[112,417]]},{"text":"策的司令部。根据过渡时期的特点，统一的方针是：在分区经营","box":[[112,434],[812,434],[812,454],[112,454]]},{"text":"的基础之上，有步骤有重点地走向统一。","box":[[111,470],[548,472],[548,493],[111,491]]},{"text":"他又说：现在是前方打仗前进，后方搞生产。后方生产，第","box":[[161,508],[812,509],[812,530],[161,529]]},{"text":"一步是要恢复，支援前方，争取全国胜利。今天还不是转人建","box":[[111,545],[813,546],[813,567],[111,566]]},{"text":"设。现在二百一十万野战军南下，加上民夫超过三百万，后方一","box":[[111,582],[812,584],[812,604],[111,602]]},{"text":"定要指定地区支援前方：以华北的大部支援西北野战军，以东北","box":[[111,620],[812,622],[812,642],[111,640]]},{"text":"加中原支援东北野战军，以华东与华北加上一点东北支援华东野","box":[[111,657],[813,660],[813,681],[111,677]]},{"text":"战军和中原野战军。中央的做法是：抓住华北，依靠东北，支援","box":[[111,696],[812,698],[812,718],[111,716]]},{"text":"前方。这样中央也坐稳了。①","box":[[110,732],[417,731],[417,755],[110,756]]},{"text":"他在发言中，对金融、交通、工业、城市接收、兵工生产等","box":[[161,771],[812,773],[812,793],[161,791]]},{"text":"各方面工作都提出了系统的意见。","box":[[110,808],[472,810],[472,830],[110,828]]},{"text":"毛泽东在七届二中全会的总结中说到：新中国中央人民政府","box":[[161,846],[811,848],[811,869],[161,867]]},{"text":"的主要人员配备，现在尚不能确定，还需要同民主人士商量，但","box":[[110,883],[812,886],[812,906],[110,903]]},{"text":"“恩来是一定要参加的，其性质是内阁总理”。②","box":[[109,920],[619,919],[619,943],[109,944]]},{"text":"在过去长期的战争环境中，各根据地的财政经济和后方勤务","box":[[160,959],[810,961],[810,981],[160,979]]},{"text":"工作有着较大的相对独立性，实行根据各自情况采取的不尽相同","box":[[110,995],[812,998],[812,1019],[110,1016]]},{"text":"的做法。在新的历史条件下，如何进一步改变这种状况，是一个","box":[[110,1033],[811,1035],[811,1056],[110,1054]]},{"text":"至关重要而又相当复杂的问题。七届二中全会后，周恩来在深入","box":[[110,1071],[812,1073],[812,1093],[110,1091]]},{"text":"①周恩来在中共七届二中全会上的发言记录，1949年3月13日。","box":[[145,1146],[690,1149],[690,1169],[144,1166]]},{"text":"②毛泽东在中共七届二中全会上的发言记录，1949年3月13日。","box":[[145,1173],[689,1176],[689,1196],[144,1193]]}],"dimensions":{"height":1347,"width":912}}