{"ocr_results":[{"text":"接见外国记者谈话这个非常偶然的机会之上，虽然问题总算得到了解决，但也","box":[[63,103],[824,101],[824,122],[63,124]]},{"text":"让人留下深刻的思考。","box":[[64,140],[276,140],[276,160],[64,160]]},{"text":"值得一提的是，早在1990年以前，某部一位党史研究室的研究员，其著作","box":[[108,176],[823,176],[823,196],[108,196]]},{"text":"中将林彪专机坠机原因说成是机组人员起义的结果。我很佩服这位不懂飞行","box":[[64,212],[823,212],[823,232],[64,232]]},{"text":"专业的研究员作出如此重要的结论。作者在分析各种原因中，对机组人员在","box":[[63,247],[823,248],[823,268],[63,267]]},{"text":"当时历史背景下所具备的思想觉悟是完全肯定的，也是完全符合实际的。作","box":[[65,284],[823,284],[823,304],[65,304]]},{"text":"者写道：“在那极左的岁月里，虽然许多革命理论和口号被登峰造极的狂热推","box":[[63,319],[823,320],[823,340],[63,339]]},{"text":"过了真理界限而变成了谬误，但广大党员和群众却是怀着虔诚的愿望去理解","box":[[61,355],[823,357],[823,377],[61,375]]},{"text":"和信奉它们的。毋庸置疑在这种特殊环境下陶冶出来的爱国主义和献身精","box":[[63,391],[822,393],[822,413],[63,411]]},{"text":"神，不管其内容多么偏激，但却相当广泛地深人人心。”作者继续写道：““九一","box":[[62,426],[823,429],[823,449],[62,447]]},{"text":"三”事件之前，一般党员群众并不知道林彪的错误，因此，以一个副统帅的身份","box":[[62,462],[821,465],[821,486],[62,483]]},{"text":"挟持一架飞机外逃，其手段可能会是欺骗、利诱、威胁。那么也应该允许机组","box":[[61,498],[821,502],[821,522],[61,518]]},{"text":"人员有一个上当一怀疑一一思想斗争—起义的过程。”这位研究员虽然不","box":[[61,534],[822,538],[822,559],[61,555]]},{"text":"是专机部队的人，但字里行间已经充满了对专机飞行员的信任与理解。回忆","box":[[62,570],[822,574],[822,595],[62,591]]},{"text":"一下，在20世纪五六十年代，还没有听说发生在客机上的劫机事件而最后使","box":[[60,605],[821,609],[821,630],[60,626]]},{"text":"劫持飞机者得遥的。我想，当这位研究员看到我对林彪专机飞行活动的一系","box":[[61,641],[821,647],[821,667],[61,661]]},{"text":"列不正常现象的分析时，一定会有同感。如果对当今劫机中机组为保全飞机","box":[[60,677],[822,683],[822,704],[60,698]]},{"text":"与乘客安全而按劫机者的意图飞往异国他乡的行为能够理解的话，同样也能","box":[[62,713],[821,720],[821,740],[62,733]]},{"text":"谅解劫持发生在重要专机上的飞行员的一切表现了。","box":[[61,750],[570,754],[570,774],[61,769]]},{"text":"谁也不敢保证自己的一生都是一帆风顺的，生活中的意外打击随时会降","box":[[106,783],[820,791],[820,814],[106,806]]},{"text":"临在每个人的头上，尤其是交通中的意外事故，会非常偶然地夺去一个人的","box":[[60,820],[821,828],[821,849],[60,841]]},{"text":"生命。","box":[[58,857],[117,857],[117,879],[58,879]]},{"text":"对于那些乘车、乘船与乘坐飞机的人们来说，谁也不能百分之百地保证不","box":[[104,893],[821,902],[821,923],[104,914]]},{"text":"发生任何问题。在每次较大空难之后的报道中，总有个别人是幸运者，无论是","box":[[59,928],[820,938],[820,958],[59,949]]},{"text":"什么原因没有买上该次航班的机票，或者是因故迟到没有赶上飞机，甚至因特","box":[[59,964],[821,974],[821,995],[59,985]]},{"text":"殊情况被乘务员赶下飞机等，只要没有登上出事的飞机，就是幸运者。可是，","box":[[58,1001],[820,1011],[820,1032],[58,1022]]},{"text":"也有本不应该乘坐出事的飞机，就是买退票也非走不可的。以上两种人都是","box":[[57,1035],[821,1047],[821,1070],[57,1058]]},{"text":"无意之中在生死线上摇摆，一念之差，就有性命之忧。","box":[[57,1072],[569,1080],[569,1103],[57,1094]]},{"text":"专机师有一位女领航员，死神曾4次向她打过招呼：在一次本场夜间复杂","box":[[103,1108],[821,1120],[821,1142],[103,1131]]},{"text":"气象的训练飞行中，为了能争取到学习的机会，在飞机停下来准备换人的时","box":[[57,1145],[820,1157],[820,1178],[57,1166]]},{"text":"候，眼看她就要登上飞机，结果因机上人多被机长赶了下来，因为都想用复杂","box":[[57,1182],[820,1194],[820,1215],[57,1203]]},{"text":"天气训练的机会亲自上天观察一下别人的飞行，这种好学的精神是非常可贵","box":[[57,1219],[820,1232],[820,1252],[57,1239]]},{"text":"的。就是这架伊尔-14飞机，换人后的第一次起飞就发生一等事故，飞机与人","box":[[56,1255],[820,1268],[820,1289],[56,1275]]},{"text":"246真相：专机副驾驶亲历“九一三","box":[[53,1298],[317,1305],[316,1324],[53,1318]]}],"dimensions":{"height":1368,"width":881}}