{"ocr_results":[{"text":"266","box":[[143,100],[172,100],[172,116],[143,116]]},{"text":"INDEX","box":[[200,99],[263,99],[263,116],[200,116]]},{"text":"Chenghai County, Guangdong, 176","box":[[144,153],[384,153],[384,174],[144,174]]},{"text":"Dao County,Hunan,238n25","box":[[467,151],[668,152],[667,173],[466,171]]},{"text":"choice: political contexts and, 15-18; and","box":[[144,176],[420,176],[420,196],[144,196]]},{"text":"Deng Xiaoping, 31, 35","box":[[467,174],[620,176],[620,196],[466,195]]},{"text":"political orientation, 11-15","box":[[168,201],[349,201],[349,218],[168,218]]},{"text":"diffusion models, 102103","box":[[468,200],[646,200],[646,217],[468,217]]},{"text":"Chongqing, Sichuan, 146-147, 168-169","box":[[143,222],[421,221],[421,241],[143,242]]},{"text":"Dongxing County, Guangxi, 99","box":[[466,221],[683,222],[683,242],[466,241]]},{"text":"Chongzuo County, Guangxi, 99","box":[[143,245],[361,244],[361,264],[143,265]]},{"text":"Cleansing of the Class Ranks campaign,","box":[[144,268],[410,268],[410,288],[144,288]]},{"text":"economic impacts,116-117","box":[[468,268],[652,268],[652,285],[468,285]]},{"text":"178184;introduction, 178;casualty","box":[[169,293],[418,293],[418,310],[169,310]]},{"text":"E1 Salvador, 190191, 191,192,193","box":[[469,294],[705,294],[705,308],[469,308]]},{"text":"and victimrates,178181,179,180,","box":[[169,317],[415,317],[415,331],[169,331]]},{"text":"237n13; comparison to other countries,","box":[[167,337],[435,336],[435,356],[167,357]]},{"text":"faction formation,108-126;introduction,22,","box":[[468,338],[763,338],[763,355],[468,355]]},{"text":"193; origins and spread, 181-182;","box":[[169,361],[401,361],[401,378],[169,378]]},{"text":"108109, 197199; in absence of power","box":[[493,360],[747,361],[747,379],[493,378]]},{"text":"purpose, 181; systematic national","box":[[166,384],[401,381],[401,402],[167,406]]},{"text":"seizure, 232n2; cellular pattern of","box":[[493,384],[711,384],[711,401],[493,401]]},{"text":"scope,182-184","box":[[167,409],[273,405],[274,424],[168,427]]},{"text":"mobilization and, 109110; conficting","box":[[491,403],[746,407],[746,428],[491,425]]},{"text":"collective action,9,10,2223,25,101-103,","box":[[144,428],[435,429],[435,446],[144,445]]},{"text":"political priorities and, 117; factions as","box":[[494,430],[739,430],[739,447],[494,447]]},{"text":"220n42","box":[[167,451],[222,451],[222,469],[167,469]]},{"text":"emergent properties, 78, 811, 12,","box":[[493,454],[721,451],[721,468],[493,471]]},{"text":"Communist Party, 25. See also party-state","box":[[143,474],[419,475],[419,493],[143,492]]},{"text":"219n30; interest group analysis, 38;","box":[[492,473],[731,474],[731,494],[492,493]]},{"text":"counties: cadres in, 90-91, 91; factional","box":[[144,498],[408,498],[408,515],[144,515]]},{"text":"military intervention in counties,122124;","box":[[494,497],[768,499],[767,517],[494,514]]},{"text":"warfare,148;military intervention,118","box":[[169,522],[432,522],[432,539],[169,539]]},{"text":"military intervention in provinces,cities,","box":[[494,520],[753,523],[753,540],[494,538]]},{"text":"119,122124; office invasions, 5354,","box":[[169,542],[423,543],[423,563],[169,562]]},{"text":"and prefectures, 120122; from opposition","box":[[493,544],[769,544],[769,564],[493,564]]},{"text":"54; opposition to power seizures,","box":[[169,569],[386,569],[386,586],[169,586]]},{"text":"to power seizures, 110111, 111116;","box":[[492,568],[745,567],[745,584],[492,585]]},{"text":"115-116;population demographics,52","box":[[170,591],[428,591],[428,608],[170,608]]},{"text":"political context and, 15-18; political","box":[[492,589],[749,588],[749,608],[492,609]]},{"text":"power seizures, 81, 81; rebel coalitions,","box":[[166,612],[425,610],[425,631],[166,634]]},{"text":"orientation as choice and, 11-15;","box":[[492,611],[717,611],[717,631],[492,631]]},{"text":"5556, 56; rebel insurgencies in agrarian","box":[[168,635],[439,635],[439,656],[168,656]]},{"text":"probabilities for faction formation,","box":[[492,636],[730,634],[730,655],[492,656]]},{"text":"counties, 75-77; rebel insurgencies in","box":[[168,659],[416,659],[416,676],[168,676]]},{"text":"128129, 129; relative to military, 67,","box":[[494,659],[745,659],[745,676],[494,676]]},{"text":"urbanized counties, 72-75; seizure of","box":[[168,682],[418,682],[418,699],[168,699]]},{"text":"108-109,116-118,118-120,124-126","box":[[495,682],[745,682],[745,696],[495,696]]},{"text":"officials,54-55,55","box":[[169,704],[296,704],[296,721],[169,721]]},{"text":"127128, 128, 155, 198199, 218n27","box":[[494,704],[733,704],[733,721],[494,721]]},{"text":"county-level cities: cadres in,90-91,91;","box":[[144,726],[408,726],[408,743],[144,743]]},{"text":"factional warfare,127-171;introduction,","box":[[468,725],[741,726],[741,744],[468,743]]},{"text":"military intervention,118,119;office","box":[[168,750],[415,750],[415,768],[168,768]]},{"text":"2223, 127, 152,199200; casualty","box":[[493,750],[731,750],[731,768],[493,768]]},{"text":"invasions, 5354, 54; power seizures in,","box":[[167,774],[430,774],[430,791],[167,791]]},{"text":"rates, 142,142143,153, 154, 163164,","box":[[491,772],[760,771],[760,791],[491,792]]},{"text":"81,81; rebel coalitions, 55-56,56; rebel","box":[[168,796],[435,796],[435,813],[168,813]]},{"text":"164; costs oflosing,155-156,167168;","box":[[493,795],[755,797],[755,814],[493,812]]},{"text":"insurgencies,70-72; seizure of officials,","box":[[167,819],[429,817],[429,835],[167,837]]},{"text":"decline in insurgency events, 152153,","box":[[492,817],[748,818],[748,839],[492,838]]},{"text":"54-55, 55","box":[[168,841],[238,841],[238,858],[168,858]]},{"text":"153; descriptions of regional violence,","box":[[495,841],[743,841],[743,861],[495,861]]},{"text":"critical mass theories,101-102,197","box":[[145,866],[379,866],[379,881],[145,881]]},{"text":"145-150; escalation in relation to","box":[[495,865],[715,865],[715,883],[495,883]]},{"text":"Cultural Revolution:introduction,1-23;","box":[[144,888],[426,888],[426,905],[144,905]]},{"text":"political settlement, 152, 161-164, 164;","box":[[491,887],[758,886],[758,906],[491,907]]},{"text":"comparison to other countries,","box":[[168,910],[380,910],[380,930],[168,930]]},{"text":"escalation trap, 152; factional divisions","box":[[492,910],[753,909],[753,929],[492,930]]},{"text":"190-191,190-194; conclusions,","box":[[169,933],[389,934],[389,951],[169,950]]},{"text":"and,5-6;factional realignment after","box":[[492,934],[738,934],[738,951],[492,951]]},{"text":"195-203;economic impacts, 116-117","box":[[168,957],[430,957],[430,974],[168,974]]},{"text":"military order to stand down, 133136;","box":[[494,957],[757,957],[757,974],[494,974]]},{"text":"factional warfare, 127-171; faction","box":[[167,976],[410,977],[410,998],[167,997]]},{"text":"family background and, 45; final","box":[[494,978],[723,978],[723,999],[494,999]]},{"text":"formation and military intervention,","box":[[167,1001],[420,1003],[420,1020],[167,1018]]},{"text":"battles, 168171; imposition of political","box":[[492,1001],[759,1001],[759,1021],[492,1021]]},{"text":"108-126; historiography gaps, 2;","box":[[167,1023],[397,1025],[397,1045],[167,1043]]},{"text":"order, 150-151; increase in collective","box":[[494,1025],[737,1025],[737,1042],[494,1042]]},{"text":"official party stance on, 207; party-state","box":[[166,1046],[441,1048],[441,1068],[166,1066]]},{"text":"violence,140-142,141; percentage","box":[[492,1047],[726,1049],[726,1067],[492,1065]]},{"text":"focus, 1821, 201203;political","box":[[168,1071],[392,1071],[392,1088],[168,1088]]},{"text":"of population involved, 183; rebel","box":[[493,1070],[719,1070],[719,1090],[493,1090]]},{"text":"mobilization,23-50; power seizures by","box":[[168,1093],[435,1094],[435,1113],[168,1112]]},{"text":"objectives, 155; regional alliances,","box":[[492,1093],[718,1092],[718,1113],[492,1114]]},{"text":"cadres, 79-107; purpose of, 1-2;rebel","box":[[169,1118],[429,1118],[429,1135],[169,1135]]},{"text":"136140; relationship to military control","box":[[494,1118],[766,1118],[766,1135],[494,1135]]},{"text":"insurgencies, 51-78; repression,","box":[[167,1140],[385,1141],[385,1159],[167,1158]]},{"text":"and political settlement, 156161,157,","box":[[494,1141],[750,1141],[750,1158],[494,1158]]},{"text":"172-194;socialstructure and,201,","box":[[170,1164],[409,1164],[409,1178],[170,1178]]},{"text":"159, 160, 161; reversal of military","box":[[493,1161],[717,1162],[717,1182],[493,1181]]},{"text":"202","box":[[168,1186],[197,1186],[197,1202],[168,1202]]},{"text":"interventionsand,129-133,143-145","box":[[494,1186],[745,1186],[745,1200],[494,1200]]},{"text":"Cultural Revolution Committees,28","box":[[144,1209],[390,1209],[390,1227],[144,1227]]},{"text":"statistical model for escalation in relation","box":[[493,1209],[766,1209],[766,1227],[493,1227]]}],"dimensions":{"height":1388,"width":919}}