{"ocr_results":[{"text":"第一章","box":[[1047,135],[1143,135],[1143,163],[1047,163]]},{"text":"走进中南海","box":[[1021,176],[1146,176],[1146,202],[1021,202]]},{"text":"五、从雪山草地走向新中国诞生","box":[[284,502],[907,496],[907,533],[285,539]]},{"text":"毛主席经常同我们谈起红军过雪山草地的艰难日子，教育","box":[[198,656],[1065,651],[1065,680],[198,685]]},{"text":"我们不能忘本，要保持艰苦奋斗本色。新中国成立初期，我们","box":[[131,720],[1067,715],[1067,745],[131,750]]},{"text":"国家很穷，他对身边人员说：“人民共和国来之不易啊！我们现","box":[[132,784],[1065,779],[1065,809],[132,814]]},{"text":"在虽然有些困难，但也不是二万五千里长征嘛，也不是雪山草","box":[[130,847],[1066,842],[1066,872],[130,877]]},{"text":"地嘛！”毛主席不知有多少次向我们谈起中国工农红军过雪山","box":[[132,913],[1065,909],[1065,936],[132,940]]},{"text":"草地的艰难。谈到动情之处，他就不由自主地流下泪来。我是","box":[[131,974],[1067,971],[1067,1001],[131,1004]]},{"text":"一个从雪山草地上走过来的红军战士，是一个幸存者，我深深","box":[[132,1036],[1069,1035],[1069,1069],[132,1070]]},{"text":"理解毛主席的这种心情。","box":[[133,1104],[492,1104],[492,1130],[133,1130]]},{"text":"红军是1935年6月开始过雪山草地的，我那时在国家保卫","box":[[201,1167],[1066,1164],[1066,1194],[201,1197]]},{"text":"局，经常见到毛主席，对这一段历史我一直记忆犹新。","box":[[133,1230],[913,1230],[913,1260],[133,1260]]},{"text":"我们经过的雪山很多，较有名的是“夹金山”。它位于四","box":[[204,1295],[1066,1293],[1066,1321],[204,1323]]},{"text":"川、西康交界区，海拔4000多米，一上一下70多华里，山上终年","box":[[137,1358],[1067,1357],[1067,1387],[137,1388]]},{"text":"积雪，有四五尺厚。长征时，我们在山上非常艰难地跋涉。毛主","box":[[134,1424],[1068,1422],[1068,1449],[134,1451]]},{"text":"席和其他中央领导同志跟我们一样，忍受着难以想象的艰难，","box":[[137,1487],[1049,1487],[1049,1514],[137,1514]]},{"text":"徒步爬上山。山上空气稀薄，严重缺氧，戀得人喘不过气来，浑","box":[[135,1551],[1069,1551],[1069,1577],[135,1577]]},{"text":"身无力。历史上很少有人从这里走过，我们翻越大雪山是一个","box":[[134,1612],[1068,1612],[1068,1642],[134,1642]]},{"text":"史无前例的壮举。红军于6月7日到达夹金山下，寒气阵阵向人","box":[[135,1678],[1066,1677],[1066,1705],[135,1706]]},{"text":"袭来，大家穿上所有的衣服开始向茫茫雪山迈进，有的人从雪","box":[[135,1742],[1069,1742],[1069,1769],[135,1769]]},{"text":"23","box":[[617,1834],[646,1834],[646,1859],[617,1859]]}],"dimensions":{"height":1939,"width":1241}}