{"ocr_results":[{"text":"康生：“枪杀了人，你现在还没有向中央报告。这件事情比","box":[[254,158],[1048,158],[1048,185],[254,185]]},{"text":"宜宾的事情要严重得多。”","box":[[190,218],[532,217],[532,244],[190,245]]},{"text":"周恩来：“3月8号你们有个镇反的报告，逮捕了多少人，","box":[[252,280],[1028,279],[1028,306],[252,307]]},{"text":"并没有说清楚。方县你们报告说只捕了600多人，这和我们了解","box":[[192,343],[1048,343],[1048,367],[192,367]]},{"text":"的差太远。”","box":[[190,400],[347,398],[347,429],[190,432]]},{"text":"康生：“你们晓不晓得这是你们军区发生的大规模的枪杀？","box":[[253,462],[1036,461],[1036,489],[253,490]]},{"text":"这是军区的问题。”","box":[[189,522],[437,520],[438,550],[189,552]]},{"text":"甘渭汉：“别的地方没有抓。”","box":[[252,584],[639,582],[639,610],[252,612]]},{"text":"周恩来：“四川的问题之所以被重视，是刘结挺同志提出，","box":[[253,646],[1030,646],[1030,673],[253,673]]},{"text":"中央才检查四川的工作。军区颠倒黑白，说成是‘镇反’工作，","box":[[192,707],[1040,707],[1040,733],[192,733]]},{"text":"实际是镇压革命。从宜宾看，是镇压革命派。每个问题再讲的时","box":[[190,767],[1048,766],[1048,793],[190,794]]},{"text":"候，不要讲那么多细节，从宜宾展开，检查全省的工作。7000","box":[[191,827],[1049,826],[1049,853],[191,854]]},{"text":"万人，是全国最大的省。万县、左灵、自贡、成都、重庆，通告","box":[[190,889],[1049,888],[1049,915],[190,916]]},{"text":"包括地方很厂了，要化一点时间，不是一、二大解决的。第一件","box":[[193,951],[1048,951],[1048,975],[193,975]]},{"text":"事：成都军区要负全责。赶快把这个事停下来，2号起，不准再","box":[[191,1011],[1049,1011],[1049,1037],[191,1037]]},{"text":"捕任何一个人，狱中的人不准伤害一个，甘、韦负责。梁兴初同","box":[[190,1070],[1048,1070],[1048,1097],[190,1097]]},{"text":"志监督，现在派梁兴初同志去做司令员，”","box":[[190,1133],[750,1131],[750,1155],[190,1157]]},{"text":"众人鼓掌。","box":[[251,1191],[389,1191],[389,1222],[251,1222]]},{"text":"周恩来继续：“马上打电话去，不能抓，要放出来，也不要","box":[[252,1254],[1049,1254],[1049,1281],[252,1281]]},{"text":"马上就放，不然会不知下落了，你们一个一个军分区打电话，军","box":[[192,1315],[1049,1315],[1049,1341],[192,1341]]},{"text":"管电话给你们，一个个军分区传达到武装部，对革命群众不能再","box":[[192,1376],[1048,1376],[1048,1400],[192,1400]]},{"text":"歧视了，对真正反革命组织要区别头头和群众，明后大要发通知。","box":[[191,1435],[1045,1437],[1045,1461],[191,1459]]},{"text":"第二，请在座的解决这个事，是局部问题，我们无产阶级文","box":[[254,1497],[1049,1497],[1049,1524],[254,1524]]},{"text":"化大革命要看大形势，要记住毛主席的话，搞文化革命要相信什","box":[[193,1559],[1048,1559],[1048,1583],[193,1583]]},{"text":"194","box":[[606,1608],[636,1608],[636,1632],[606,1632]]}],"dimensions":{"height":1754,"width":1241}}