{"ocr_results":[{"text":"的秘书，到了李井泉住宿的瑞金街招待所。有公安人员引路，他","box":[[193,160],[1048,160],[1048,184],[193,184]]},{"text":"们顺利进了大门。进去时，李并泉的随行人员止在楼下餐厅里准","box":[[193,221],[1048,221],[1048,244],[193,244]]},{"text":"备用早餐。“战斗小组”要这些工作人员交出李井泉，教育他们","box":[[191,280],[1049,280],[1049,307],[191,307]]},{"text":"“站到毛主席革命路线一边来，同走资本主义道路当权派划清界","box":[[202,340],[1048,342],[1048,369],[202,367]]},{"text":"限。”","box":[[185,399],[257,395],[259,433],[187,437]]},{"text":"但是，仍有人流露出抵触情绪，觉得自己的职责所在，不愿","box":[[241,463],[1049,463],[1049,490],[241,490]]},{"text":"意配合红卫兵的行动。红卫兵便不客气的质问：“你是保卫毛主","box":[[191,523],[1049,523],[1049,550],[191,550]]},{"text":"席还是保卫李井泉？”","box":[[188,583],[486,578],[486,612],[188,617]]},{"text":"人们当然要站在毛泽东这一边。","box":[[243,648],[653,648],[653,672],[243,672]]},{"text":"随后，“战斗小组”留下儿人继续对李并泉的随员做工","box":[[303,707],[1050,707],[1050,733],[303,733]]},{"text":"作，其他人与上海公安局的3个造反派一起直奔二楼房间，顺利","box":[[191,767],[1049,766],[1049,793],[191,794]]},{"text":"找到了李并泉。他们先对李并泉进行了搜查，然后拿出中央电报","box":[[191,829],[1047,829],[1047,853],[191,853]]},{"text":"给他看，并向他宣布，要将他押回四川批判。","box":[[192,890],[791,890],[791,914],[192,914]]},{"text":"李并泉未对电报表示任何怀疑，只是提出应等医院体检","box":[[304,951],[1048,951],[1048,975],[304,975]]},{"text":"表拿到后再走，这自然被红卫兵学生认为是“耍花招”而否决","box":[[190,1010],[1049,1011],[1049,1037],[190,1036]]},{"text":"了。","box":[[188,1067],[237,1067],[237,1103],[188,1103]]},{"text":"早饭后，“战斗小组”负责人、重庆大学红卫兵向李井","box":[[302,1130],[1050,1130],[1050,1160],[302,1160]]},{"text":"泉一行宣布：从现在起，一切听他们指挥。李井泉和秘书、警卫","box":[[191,1194],[1049,1194],[1049,1218],[191,1218]]},{"text":"员及医生一人跟他们一起回四川，其他3名随员，在他们走后","box":[[192,1254],[1049,1254],[1049,1281],[192,1281]]},{"text":"24小时内不得离开招待所，不得向外打电报、电话，然后自行","box":[[189,1313],[1049,1315],[1049,1341],[189,1340]]},{"text":"回川，到成都向驻四川大学的“重庆大学八一五战斗团赴蓉挺进","box":[[194,1376],[1048,1376],[1048,1400],[194,1400]]},{"text":"纵队”报到。并且警告：“若有违抗，后果自负。”","box":[[190,1434],[860,1432],[860,1463],[190,1465]]},{"text":"其间，还发生了一个小插曲：李并泉的一位随员，在听了造","box":[[242,1498],[1049,1498],[1049,1522],[242,1522]]},{"text":"反派宣传后，为表明自己与李井泉划清了界限和坚决站到毛主席","box":[[193,1559],[1046,1559],[1046,1583],[193,1583]]},{"text":"195","box":[[607,1610],[635,1610],[635,1631],[607,1631]]}],"dimensions":{"height":1754,"width":1241}}