{"ocr_results":[{"text":"坏国家财产，罪责难逃！”。","box":[[187,163],[580,167],[580,204],[187,200]]},{"text":"喊了一阵之后，袁占山挣扎着爬了起来，用力推开了变形的","box":[[252,236],[1049,235],[1049,263],[252,264]]},{"text":"门，撤到了走廊。这时枪声停了，环顾四看，眼前已面目全非，","box":[[191,301],[1040,301],[1040,331],[191,331]]},{"text":"走廊内尘土飞扬，各屋的门七扭八歪，墙壁出现了一道道的裂缝，","box":[[191,367],[1043,366],[1043,394],[191,395]]},{"text":"广播室北边的走廊还在冒着蓝烟。他走近冒烟处一看，一下子傻","box":[[190,433],[1049,433],[1049,460],[190,460]]},{"text":"眼了：楼梯已不见了·····他顾不上再多想，第一个念头是马上逃","box":[[191,497],[1048,496],[1048,523],[191,525]]},{"text":"走！怎么逃？南面已被人占领，北面已无路可走，唯一的逃生办","box":[[191,561],[1048,561],[1048,588],[191,588]]},{"text":"法就是跳楼！楼板距地面近4米，如直接跳向地面，弄不好会受","box":[[190,626],[1049,627],[1049,654],[190,653]]},{"text":"伤。他向下瞄了瞄，发现了一块略呈三角形的白色天棚板，这块","box":[[191,693],[1049,693],[1049,720],[191,720]]},{"text":"大棚板是爆炸时从楼梯上方的天棚上震落下来的，它一头紧贴地","box":[[192,760],[1047,760],[1047,784],[192,784]]},{"text":"面，另一头斜搭在坍塌的楼梯碎块上，约1米见方。于是，袁占","box":[[192,824],[1049,824],[1049,851],[192,851]]},{"text":"山战战兢兢地向它跳了下去。“噗刺”一声，脚下溅起了一团白","box":[[191,885],[1049,886],[1049,916],[191,915]]},{"text":"烟，他止好落在了这块大棚板上，把它砸了个大窟窿，脚也落到","box":[[192,953],[1050,953],[1050,980],[192,980]]},{"text":"了地面。他动了动脚，没有受伤！不由心头一阵惊喜，忙从废墟","box":[[194,1018],[1050,1018],[1050,1045],[194,1045]]},{"text":"里爬了出来。向上一望，儿个实验中学的学生还在楼板的豁口处","box":[[193,1083],[1050,1083],[1050,1110],[193,1110]]},{"text":"向下观望，犹豫，不敢跳。袁占山忙招呼他们赶快下来。有个胆","box":[[192,1147],[1048,1147],[1048,1174],[192,1174]]},{"text":"子大的也跟着跳了下来，还有的攀着断壁残墙爬到了地面。","box":[[194,1214],[976,1214],[976,1240],[194,1240]]},{"text":"这时，他们发现没逃出的伙伴正从南边撤退，被几个拿枪的","box":[[251,1275],[1050,1276],[1050,1306],[251,1305]]},{"text":"人堵在院子里。院子里还停着一辆卡车，一些陌生人正在往车上","box":[[191,1342],[1050,1342],[1050,1372],[191,1372]]},{"text":"扔枪。不能管这些了，逃命要紧！他们儿个人一窝蜂式地冲过中","box":[[192,1408],[1047,1408],[1047,1435],[192,1435]]},{"text":"央大街，跑到对面的锦州饭店楼前的人行道上。回首望去，爆炸","box":[[192,1473],[1049,1473],[1049,1500],[192,1500]]},{"text":"的废墟还在冒着烟。围观的群众都是“老糟”，一下子围了过来，","box":[[192,1537],[1046,1537],[1046,1567],[192,1567]]},{"text":"181","box":[[606,1609],[635,1609],[635,1634],[606,1634]]}],"dimensions":{"height":1755,"width":1240}}