{"ocr_results":[{"text":"锋枪声。“422”的广播喇叭被炸哑了，南宁市上空只有“联指之","box":[[190,170],[1048,171],[1048,198],[190,197]]},{"text":"声”在广播：","box":[[186,232],[357,232],[357,266],[186,266]]},{"text":"“‘422’一小撮阶级敌人，杀害我‘联指’战士，手段野","box":[[260,293],[1053,298],[1053,335],[260,330]]},{"text":"蛮，罪恶滔天，今天他们又制造了一起震撼天下的血案······今天","box":[[190,365],[1050,365],[1050,395],[190,395]]},{"text":"下午18点55分，解放路的土匪们竟敢向我敬爱的解放军开枪升","box":[[195,433],[1048,433],[1048,457],[195,457]]},{"text":"炮，把炮打到广西军区大院内，致使我解放军多人伤亡，是可忍，","box":[[190,497],[1045,497],[1045,524],[190,524]]},{"text":"敦不可忍…·.”","box":[[188,560],[395,552],[396,587],[190,595]]},{"text":"当大晚上，厂西自治区革筹小组和广西军区向中央、中央军","box":[[255,628],[1048,628],[1048,652],[255,652]]},{"text":"委、中央文革发出《贯彻“七三布告”情况简报之八》说：“17","box":[[190,693],[1049,693],[1049,720],[190,720]]},{"text":"点55分至19点30分，解放路的广西‘422’向军区开炮。军区","box":[[191,757],[1048,756],[1048,784],[191,785]]},{"text":"院内中弹5发，打伤战士2人。”","box":[[190,821],[628,819],[628,849],[190,851]]},{"text":"314","box":[[603,1609],[637,1609],[637,1634],[603,1634]]}],"dimensions":{"height":1755,"width":1240}}