{"ocr_results":[{"text":"第十二章“梁效”的後事","box":[[571,103],[790,103],[790,120],[571,120]]},{"text":"批判”。粉碎“四人”以後，我在哲學系當家。13","box":[[134,180],[630,176],[631,203],[134,207]]},{"text":"我是“大批判”的受害者，對“大批判”深痛，當然不會再","box":[[181,224],[790,224],[790,241],[181,241]]},{"text":"以“大批判”来害人。群要求批判友蘭，我拖著不辦。反正不會","box":[[138,258],[789,258],[789,276],[138,276]]},{"text":"有人我“包庇梁效”。","box":[[135,290],[367,291],[367,311],[135,310]]},{"text":"倒是馮友蘭本人，又耐不住了，適時表熊是他的習性。1977年4","box":[[179,330],[794,331],[794,351],[179,350]]},{"text":"月15日，《毛澤東選集》第五卷發行。5月4日，馮友蘭就交了一份","box":[[136,364],[789,365],[789,386],[136,385]]},{"text":"题爲《在工作中学，在工作中批判》的学《毛澤東選集》第五卷","box":[[137,401],[790,401],[790,418],[137,418]]},{"text":"心得。（《友蘭先生年譜長编》未記此事。）哲学系教肺王永江、","box":[[138,435],[777,435],[777,452],[138,452]]},{"text":"陳偉寫了一篇《計“梁效”某顧問》，對照友蘭吹捧江青的《","box":[[138,469],[790,469],[790,487],[138,487]]},{"text":"史》詩，批判《在工作中學習，在工作中批判》，發表於《歷史研","box":[[137,501],[790,502],[790,522],[137,521]]},{"text":"究》1977年第4期。5月7日，委統戴部将馮发蘭的心得報送北京","box":[[140,539],[789,539],[789,553],[140,553]]},{"text":"市委。市委負责人丁國鈺、黄作珍、買汀、徐運北大喜過望，作","box":[[139,571],[789,571],[789,589],[139,589]]},{"text":"了批語，對馮友蘭進行表揚：一是批了江青，二是學了毛選第五卷。","box":[[138,604],[779,605],[779,623],[138,622]]},{"text":"北京市委又將馮友蘭的心得報送中央。中央没有表示。","box":[[138,639],[691,639],[691,656],[138,656]]},{"text":"北京市委負责人的這種態度，激怒了群。7月9日，哲學系中","box":[[179,678],[790,677],[790,698],[179,699]]},{"text":"13《馮友蘭先生年譜长编》下册（北京，中華書局，2014）的1977一1978年部","box":[[135,783],[791,784],[791,803],[135,801]]},{"text":"分提到“郭基”每冠以“哲学系黛總支書記”的頭衡，。我在哲学系富","box":[[157,811],[789,811],[789,825],[157,825]]},{"text":"家，但亚非黛總支書記。哲學系的總支、革委會繁跟“四人”，維護","box":[[157,834],[790,834],[790,851],[157,851]]},{"text":"“梁效”，群為他們没有资格领導揭批“四人帮”和“梁效”的運動，","box":[[159,855],[780,856],[780,876],[159,875]]},{"text":"全系師生員工遂自發地選翠成立一個“連動领導小組”，由5人組成（3個教","box":[[157,882],[791,882],[791,899],[157,899]]},{"text":"師是我、王贵秀、李真，一個學生杨永祺，一個乾部任寧芬），我被推為","box":[[156,906],[790,906],[790,924],[156,924]]},{"text":"組長。哲學系歷来是北大的带頭羊，而後继哲學系成立“連動领導小組”的","box":[[156,931],[790,931],[790,948],[156,948]]},{"text":"還有經濟系、法律系、數學系、化學系、生物系、制藥廠，共7个單位。在這","box":[[156,955],[791,955],[791,972],[156,972]]},{"text":"7個单位，“連動领導小組”部分地奪了黛總支的權。黛總支不领導連動，但","box":[[155,981],[789,981],[789,995],[155,995]]},{"text":"仍負责日常工作。因為總支、革委會講話没人，一些亚非“連勤”的重","box":[[158,1005],[789,1005],[789,1020],[158,1020]]},{"text":"大工作群農也要求“遵勤领導小组”来领導。例如涨工资。1978年涨工资规","box":[[157,1029],[791,1029],[791,1046],[157,1046]]},{"text":"定的指標是40%，不講道理、不講條件，個個單位都是40%！每個單位，人人","box":[[157,1053],[790,1053],[790,1070],[157,1070]]},{"text":"都為自己是属於40%，那就成了100%，不好瓣！哲學系的群對薰總支、革","box":[[157,1077],[790,1077],[790,1094],[157,1094]]},{"text":"委會信不過，就請“連動领導小組”出馬。我在動員會上宣怖：“我是属於","box":[[157,1101],[790,1101],[790,1118],[157,1118]]},{"text":"60%，大家不要提名我。”我表了這個態，話就能服。涨工资在别的系打","box":[[156,1126],[790,1126],[790,1143],[156,1143]]},{"text":"破了頭，哲學系顺利結束。委予表揚，委副書記高鐵在全校幹部會","box":[[156,1150],[790,1150],[790,1167],[156,1167]]},{"text":"上宣怖：哲學系的三駕馬車由“運動领導小組”牵頭。粉碎“四人”以","box":[[155,1172],[791,1173],[791,1193],[155,1192]]},{"text":"前，我靠遗站已經將近一年；粉碎“四人帮”以後，人“哲學系臨時政府","box":[[157,1198],[790,1198],[790,1215],[157,1215]]},{"text":"首腦”。","box":[[156,1221],[223,1224],[223,1242],[155,1239]]},{"text":"335","box":[[448,1273],[479,1273],[479,1292],[448,1292]]}],"dimensions":{"height":1389,"width":920}}