{"ocr_results":[{"text":"1943年7月","box":[[832,225],[1074,223],[1075,260],[833,262]]},{"text":"457","box":[[1582,241],[1645,241],[1645,285],[1582,285]]},{"text":"风、精兵简政、统一领导、拥政爱民、发展生产、审查干部六大","box":[[242,324],[1675,337],[1674,402],[241,390]]},{"text":"政策外，并须利用这次事件迅速进行下列各项工作：（一）实行","box":[[241,406],[1673,418],[1672,480],[240,468]]},{"text":"政治攻势，打击国民党的反共气焰。（二）在军事上实行必要的","box":[[244,488],[1669,499],[1669,556],[243,545]]},{"text":"准备，调若干兵力来边区及晋西北，加强军事技术训练，组织机","box":[[242,564],[1673,576],[1672,638],[241,626]]},{"text":"关自卫军及加强民兵工作。（三）加紧进行清查特务奸细的普遍","box":[[243,645],[1669,655],[1669,714],[242,704]]},{"text":"突击运动与反特务的宣传教育工作。（四）加强党内与人民中的","box":[[245,730],[1667,737],[1667,789],[244,783]]},{"text":"阶级教育。（五）进行揭露国民党种种罪恶行为与反动思想、政","box":[[245,807],[1670,815],[1670,871],[244,862]]},{"text":"策的宣传工作，以对抗国民党的反革命宣传。","box":[[248,895],[1239,895],[1239,938],[248,938]]},{"text":"同日《","box":[[342,971],[541,971],[541,1024],[342,1024]]},{"text":"《解放日报》发表毛泽东写的关于中国政治黑暗，抗","box":[[511,968],[1669,975],[1669,1027],[511,1019]]},{"text":"战不力，英美盟邦大不满意的新闻稿。新闻稿说：英、美人士对","box":[[245,1048],[1669,1054],[1669,1105],[244,1099]]},{"text":"中国政治黑暗，和蒋介石将美、英援助不用在前线打日本而用在","box":[[245,1127],[1668,1132],[1668,1183],[244,1178]]},{"text":"补充后方部队，大不满意。最近熊式辉〔1〕在纽约、华盛顿、","box":[[245,1203],[1675,1208],[1674,1264],[244,1258]]},{"text":"伦敦的招待会上，都在这些方面受到英、美人士的质询。英、美","box":[[248,1288],[1670,1290],[1670,1338],[248,1336]]},{"text":"向熊式辉表示，在这种情况下不能以大量的武器继续援助国民党","box":[[250,1367],[1668,1371],[1668,1417],[250,1414]]},{"text":"政府。","box":[[242,1442],[391,1445],[390,1499],[241,1496]]},{"text":"同日至","box":[[348,1528],[517,1528],[517,1574],[348,1574]]},{"text":"致电董必武，指出：你的工作很得力。由于种种原","box":[[491,1528],[1669,1529],[1669,1573],[491,1572]]},{"text":"因，蒋介石在七月十日不得不电胡宗南改变进攻陕甘宁边区的决","box":[[250,1606],[1669,1608],[1669,1651],[250,1649]]},{"text":"心，现在内战危机或可避免。延安民众大会通电已于九日用万万","box":[[251,1689],[1665,1689],[1665,1726],[251,1726]]},{"text":"火急电发蒋、胡及各方要人，故你处仍应密印散发，表示共产国","box":[[250,1766],[1666,1765],[1666,1806],[250,1807]]},{"text":"际解散后我方之强硬姿态，借以击退国民党之无耻反共宣传。","box":[[251,1844],[1598,1844],[1598,1888],[251,1888]]},{"text":"同日致电周子健，指出：“蒋、胡秘密调兵准备进攻，你","box":[[349,1921],[1672,1921],[1672,1968],[349,1968]]},{"text":"们所得情报完全正确，帮助中央甚大。现经我们揭穿，已引起各","box":[[251,2001],[1669,2000],[1669,2043],[251,2044]]},{"text":"国大使干涉，我们又积极准备应战，故迫得蒋不得不于十日改变","box":[[252,2077],[1672,2076],[1672,2120],[252,2122]]},{"text":"计划”。“为击破国民党的无耻反共宣传计，你们仍应将延安民众","box":[[249,2155],[1671,2154],[1671,2199],[249,2200]]},{"text":"大会通电密发社会各方，不得停止不发。”","box":[[249,2235],[1158,2235],[1158,2278],[249,2278]]},{"text":"[1]熊式辉，当时任国民党政府军事委员会委员、驻美国军事代表团团长。","box":[[257,2395],[1657,2394],[1657,2435],[257,2436]]}],"dimensions":{"height":2717,"width":1895}}