{"ocr_results":[{"text":"4失意者们，团结起来：“文革”的“资本主义”复辟","box":[[365,129],[764,129],[764,146],[365,146]]},{"text":"社会主义事业抹黑。而张书记的命令被基层干部严格地予以执行，其后果","box":[[59,204],[764,205],[764,223],[59,222]]},{"text":"是可以想象的。①","box":[[57,241],[217,238],[218,259],[58,262]]},{"text":"事后看来，像“大跃进”这样的政治运动所造成的后果，对在地方权力结","box":[[101,277],[763,278],[763,295],[101,294]]},{"text":"构中占据主导地位的南下干部来说，实际上是一把双刃剑。一方面，它所提","box":[[58,312],[763,313],[763,333],[58,332]]},{"text":"供的政治机会会被这些处处占有政治主动权的政治精英所充分利用，以进","box":[[60,349],[764,350],[764,370],[60,369]]},{"text":"一步扩大和巩固自已的权力优势。另一方面，这些处于权力核心的地方政","box":[[60,388],[764,388],[764,404],[60,404]]},{"text":"治精英又不得不紧跟上面所下达的各种“左”倾政策和命令，在当地造成极","box":[[61,424],[762,424],[762,441],[61,441]]},{"text":"为恶劣的社会和经济后果，这反而会极大地损害地方领导在群众中的声誉","box":[[61,461],[764,461],[764,478],[61,478]]},{"text":"和威信，客观上反而巩固了地方游击队十部的群众基础，加强了后一十部群","box":[[61,498],[763,498],[763,514],[61,514]]},{"text":"体的政治支持力量。","box":[[59,531],[243,532],[243,552],[59,551]]},{"text":"对地方游击队十部而言，这种高压式的政治运动也是一个严酷的考验。","box":[[102,570],[765,570],[765,587],[102,587]]},{"text":"如果不顺从上级所中意的政策，则很容易被贴上各种政治标签而遭到打击","box":[[61,605],[764,606],[764,624],[61,623]]},{"text":"和惩罚。但如果不加保留地执行上级政策，却无法保证这种“投名状”式的","box":[[61,642],[764,642],[764,659],[61,659]]},{"text":"政治赌博获得足够的政治回报。这不仅是因为政治资源总量在当时的政","box":[[61,679],[765,679],[765,696],[61,696]]},{"text":"治、经济条件下本来就十分有限，而且也由于占主导地位的南下干部群体本","box":[[60,714],[765,713],[765,733],[60,734]]},{"text":"身就垄断了大部分的政治资源，能留给外围的基层干部的资源实际上并不","box":[[62,751],[765,751],[765,768],[62,768]]},{"text":"具备很大的吸引力。不仅如此，地方基层干部为了取得上级的信任和争取","box":[[61,789],[766,789],[766,806],[61,806]]},{"text":"表现，就必须执行不利于群众利益的经济政策，这无疑是向上级发出的一个","box":[[62,825],[764,825],[764,842],[62,842]]},{"text":"可置信的“忠诚”信号，但却直接损害到了自己现有的政治生存基础，而这种","box":[[62,861],[765,861],[765,878],[62,878]]},{"text":"冒险行为却无法保证得到足够的政治利益。更糟糕的是，如上一章所介绍","box":[[62,897],[766,897],[766,914],[62,914]]},{"text":"的那样，一旦形势有变，这些在前一阶段急着交出“投名状”的干部很可能就","box":[[62,934],[767,934],[767,951],[62,951]]},{"text":"会被当作错误政策的替罪羊而被抛弃，而此时他们却无法再反过头来希望","box":[[63,970],[767,970],[767,987],[63,987]]},{"text":"以前的政治支持者继续为他们提供政治支持。事实上，“大跌进”失败后，在","box":[[62,1006],[767,1006],[767,1023],[62,1023]]},{"text":"接鐘而来的“四清”运动中，那些在“大跃进”中积极紧跟上级的地方干部几","box":[[61,1043],[767,1042],[767,1060],[61,1061]]},{"text":"乎无一例外地吃了大亏，既没有得到来自上级的保护，又被自上而下发动的","box":[[63,1080],[765,1080],[765,1096],[63,1096]]},{"text":"群众运动整得灰头土脸，两面不讨好。","box":[[62,1116],[408,1116],[408,1133],[62,1133]]},{"text":"因此，即使在“大跌进”运动中，大多数地方十部在权衡利弊之后也仍然","box":[[104,1153],[766,1153],[766,1170],[104,1170]]},{"text":"采取了折中的办法，即在执行上级政策的过程中，在力所能及的范围内照顾","box":[[63,1189],[767,1189],[767,1205],[63,1205]]},{"text":"①来自作者2009年7月在丽水的访谈。","box":[[61,1260],[408,1260],[408,1277],[61,1277]]},{"text":"113","box":[[783,1306],[816,1306],[816,1325],[783,1325]]}],"dimensions":{"height":1364,"width":890}}