{"ocr_results":[{"text":"2浙江的共产主义革命与1949年后的权力格局","box":[[359,130],[749,130],[749,147],[359,147]]},{"text":"19个解放区之一，拥有近400万人口和近1万多人的武装力量。（同上，","box":[[43,203],[748,204],[748,224],[43,223]]},{"text":"第486页）","box":[[44,242],[140,242],[140,260],[44,260]]},{"text":"2.1.3游击武装的鼎盛时期（1946一1949年）","box":[[42,296],[464,297],[464,315],[42,314]]},{"text":"1945年8月日本投降后，在全国人民渴望和平的呼声中，国共两党在重","box":[[87,352],[749,352],[749,369],[87,369]]},{"text":"庆展开谈判。根据两党最终达成的协定，中共需让出南方八个解放区，并把","box":[[45,389],[748,389],[748,405],[45,405]]},{"text":"部队撤到陇海路以北并向苏北、皖北集中。之后，浙西、浙东的新四军部队","box":[[46,425],[748,425],[748,442],[46,442]]},{"text":"大部撤至江北，浙南游击队则在浙南继续坚守。（同上，第493一502页）","box":[[46,462],[707,462],[707,479],[46,479]]},{"text":"不过，国共两党之间的和平并没有持续多久。停战协定签订后不到一","box":[[88,499],[748,499],[748,515],[88,515]]},{"text":"年，全面内战就于1946年6月爆发了。由于在抗战期间打下了良好的基础，","box":[[46,535],[748,535],[748,552],[46,552]]},{"text":"以浙东和浙南为中心，中共在浙江境内迅速恢复了活动并持续壮大力量。","box":[[46,572],[750,572],[750,589],[46,589]]},{"text":"1948年，浙东、浙西南和浙南的游击队分别改编为浙东游击纵队第三支队、","box":[[46,609],[750,609],[750,625],[46,625]]},{"text":"浙南人民解放军第三支队和中国人民解放军浙南游击纵队，其中浙东和浙","box":[[46,645],[750,645],[750,662],[46,662]]},{"text":"南的武装力量最为强大。至1948年末，浙东游击队的规模已有6000余人，","box":[[45,681],[749,680],[749,698],[45,699]]},{"text":"而浙南游击队的武装人员则达方人之众。①不仅如此，各个游击区不再是孤","box":[[47,719],[751,719],[751,736],[47,736]]},{"text":"立作战，而是彼此协调和互相支援。国民党部队则反而被分割压缩在县城","box":[[47,755],[751,755],[751,772],[47,772]]},{"text":"里，面临着中共游击武装的不断蚕食和进攻。","box":[[47,792],[456,792],[456,809],[47,809]]},{"text":"浙江的游击队不仅在军事上已经占据上风，在政治上也开始为解放后接","box":[[88,829],[751,829],[751,846],[88,846]]},{"text":"管政权进行了大量准备。在1948年末和1949年初，浙江已经有大片区域处","box":[[47,865],[750,865],[750,882],[47,882]]},{"text":"在游击队的直接控制之下，对这些地区如何进行有效的行政管辖，是摆在游","box":[[47,902],[751,902],[751,919],[47,919]]},{"text":"击队武装面前的一个现实任务。在这方面，游击队的领袖们已经积累了丰","box":[[46,937],[751,936],[751,956],[46,957]]},{"text":"富的经验。例如，早在抗战期间，浙东的游击武装已经在其控制范围内建立","box":[[48,974],[751,974],[751,991],[48,991]]},{"text":"了抗日民主政府。随着游击队在解放战争期间不断发展，他们也迅速在新","box":[[48,1011],[752,1010],[752,1028],[48,1029]]},{"text":"的控制区域内建立起基层政权以有效行使行政权力，例如在此期间成立的","box":[[47,1048],[751,1047],[751,1065],[47,1066]]},{"text":"嵊新奉办事处、金（华）一义（乌）县政府、（富春）江东县政府等。（中共浙江","box":[[46,1083],[753,1082],[753,1102],[46,1103]]},{"text":"省委党史研究室，2002，第621页）","box":[[47,1122],[360,1121],[360,1139],[47,1140]]},{"text":"除了通过军事胜利再进行行政接管这一途径之外，浙江的游击武装还通","box":[[86,1157],[752,1156],[752,1176],[86,1177]]},{"text":"①浙东游击队的正式编号为浙东人民解放军第二游击纵队，浙南游击队的正式编","box":[[44,1229],[754,1228],[754,1248],[44,1249]]},{"text":"号为浙南人民解放军第三支队。《浙江省军事志》，第194一195页。","box":[[83,1259],[641,1258],[641,1276],[83,1277]]},{"text":"43","box":[[773,1304],[798,1304],[798,1324],[773,1324]]}],"dimensions":{"height":1364,"width":890}}