{"ocr_results":[{"text":"林彪事件完整调查D554","box":[[719,267],[1178,267],[1178,301],[719,301]]},{"text":"第三部人民大會堂D55","box":[[2232,264],[2759,243],[2760,285],[2234,305]]},{"text":"一般黄永勝出差，都要提前講，不過費四金·因盒出","box":[[485,490],[1542,492],[1542,527],[485,525]]},{"text":"就是四年，喜糖都長了毛。","box":[[1953,499],[2477,482],[2479,519],[1954,537]]},{"text":"差不是一大网大，黄永勝起碼要帶換洗衣服以及一堆藥·每","box":[[398,567],[1541,567],[1541,600],[398,600]]},{"text":"專案組把費四金当成“重點”。先是關在“亚療”一年，然","box":[[2042,570],[3100,533],[3101,572],[2043,609]]},{"text":"次出差前黄永勝都要：小費，要出差。費四金就備行李，","box":[[393,639],[1542,637],[1542,674],[394,677]]},{"text":"後關到團河晨場三年·解除關押後費四金在基層部过渡一","box":[[1956,648],[3100,608],[3101,646],[1957,686]]},{"text":"把要带的装進旅行箱，把要吃的藥准磺好。但這一次，黄永","box":[[395,716],[1538,716],[1538,748],[395,748]]},{"text":"下，轉業到地方，最後的職務“升”到北京汽車造廠再就業","box":[[1959,722],[3106,684],[3107,721],[1960,759]]},{"text":"勝一句話也没·寶四金盒黄永勝肯定没有去廣州的打","box":[[393,791],[1539,791],[1539,823],[393,823]]},{"text":"中心当主任。不管在部還是在地方，著黄永勝這個“大","box":[[1960,796],[3107,757],[3108,795],[1961,833]]},{"text":"算。","box":[[388,858],[511,858],[511,903],[388,903]]},{"text":"包袱”，人家都不敢使用。如果費四金“曲線救國”，那就立","box":[[1963,870],[3108,833],[3110,870],[1964,907]]},{"text":"9月12日晚上，費四金跟著黄永勝到人民大會堂，一","box":[[476,935],[1523,936],[1523,974],[476,972]]},{"text":"了“大功”，決不會是如此遭遇，但費四金至今不悔。[21]","box":[[1966,943],[3068,906],[3069,945],[1967,982]]},{"text":"直到第三天士回來。黄永勝情低落，回到西山，他烧了一","box":[[392,1011],[1530,1010],[1530,1043],[392,1045]]},{"text":"9月24日，黄永勝被叫到人民大會堂开會，此失去","box":[[2051,1014],[3112,980],[3114,1018],[2052,1052]]},{"text":"些照片和文件。費四金然知道跑了一架大飛機，但他一直","box":[[389,1082],[1538,1085],[1538,1123],[389,1120]]},{"text":"自由·被抓時，黄永勝大叫冤枉，那聲音很多人都到了。","box":[[1970,1094],[3112,1053],[3114,1090],[1971,1131]]},{"text":"不知道是林彪跑了，以是吴法慧跑了·因盒黄永勝的秘書","box":[[393,1162],[1537,1162],[1537,1195],[393,1195]]},{"text":"抓他们的理由是他们不揭發。可是，黄吴李邱揭發什呢？","box":[[1970,1166],[3107,1128],[3108,1165],[1971,1204]]},{"text":"老吴那天没去人民大會堂，問小費都参加大會堂的會了？","box":[[393,1235],[1527,1235],[1527,1269],[393,1269]]},{"text":"他們根本没有想到揭發·尤其是黄永勝，一没上山，二没發","box":[[1971,1241],[3118,1203],[3119,1239],[1972,1278]]},{"text":"費四金没见到吴法患，所以印象特别深·直到費四金進了學","box":[[388,1311],[1532,1311],[1532,1344],[388,1344]]},{"text":"言，有什錯？非检讨，就吧·讨内容與汪東興差","box":[[1972,1315],[3122,1277],[3123,1314],[1974,1353]]},{"text":"智班，知道原來黄永勝也有問题。","box":[[391,1384],[1095,1384],[1095,1418],[391,1418]]},{"text":"不多，汪東興过了，他們的讨一遍一遍過不了關·最","box":[[1974,1390],[3123,1352],[3125,1390],[1975,1428]]},{"text":"正像費四金的那樣，他立不是黄永勝的“心腹”，比起","box":[[478,1460],[1532,1460],[1532,1492],[478,1492]]},{"text":"後算老人家高抬貴手，過了。接下來又没有犯新的錯","box":[[1975,1464],[3125,1426],[3126,1462],[1976,1500]]},{"text":"李文普和林彪的漫長係，費四金和黄永勝要短暂得多·他","box":[[388,1532],[1534,1532],[1534,1566],[388,1566]]},{"text":"，再讨什呢？而且毛澤東南巡時還要與林彪谈，","box":[[1977,1538],[3126,1500],[3127,1537],[1978,1576]]},{"text":"出身於廣州軍區41軍121師，1968年黄永勝廣州到北","box":[[385,1603],[1534,1605],[1534,1642],[385,1641]]},{"text":"他們揭發林彪什座呢？在漫長的十年裹，黄永勝始終不","box":[[1971,1612],[3128,1572],[3129,1610],[1972,1650]]},{"text":"京，他也跟來了，是黄永勝辦公室工作人員中時間最長的。","box":[[385,1680],[1532,1678],[1532,1712],[385,1713]]},{"text":"改口。","box":[[1979,1686],[2103,1681],[2105,1721],[1981,1726]]},{"text":"跟黄永勝調到北京的工作人真都先後走了，费四金也在交","box":[[387,1755],[1531,1755],[1531,1788],[387,1788]]},{"text":"黄春光回憶：仍被關押的父親對我们，我不知道，我","box":[[2073,1758],[3133,1723],[3134,1759],[2074,1794]]},{"text":"班，備到軍委瓣公警備處·接班的警備参小湯基本上","box":[[384,1830],[1530,1830],[1530,1864],[384,1864]]},{"text":"怎知道他们要跑？父親小打仗，没有政治门争經驗。不","box":[[1988,1836],[3134,1796],[3136,1834],[1989,1874]]},{"text":"都接手了，只剩下一些經湾還没交·如果早雨天費四金走","box":[[385,1904],[1528,1904],[1528,1937],[385,1937]]},{"text":"是他胡，他根本不知道害毛主席。事實與罪名無，打","box":[[1988,1909],[3139,1870],[3140,1908],[1989,1946]]},{"text":"就走了，没想到九一三事件不期而遇，再也没走成·費四金","box":[[384,1978],[1530,1978],[1530,2011],[384,2011]]},{"text":"倒是黄永勝字？没有過任何一個打倒的文件·黄永勝","box":[[1990,1984],[3140,1945],[3141,1982],[1992,2020]]},{"text":"交完班，備回家結婚·結婚證领了，回家的火車票也拿到","box":[[382,2050],[1531,2047],[1531,2085],[382,2088]]},{"text":"领導專案組是接過周理和杨成武的，他们都基本搞定了，","box":[[1992,2058],[3140,2018],[3141,2055],[1993,2095]]},{"text":"了手，喜糖什座的也買了，被突然關了起來。","box":[[381,2124],[1317,2123],[1317,2160],[381,2162]]},{"text":"没有更多的事了·開除彭德懷黛籍，呈主席、林副主席批示，","box":[[1992,2131],[3143,2092],[3144,2129],[1993,2169]]},{"text":"費四金告家裹臨時出差，火車票也退了·這一“臨時”","box":[[471,2199],[1530,2197],[1530,2234],[471,2237]]},{"text":"這就算迫害？九一三事件後，也没有解放彭德懷嘛，彭德懷","box":[[1995,2207],[3146,2168],[3147,2205],[1996,2243]]}],"dimensions":{"height":2496,"width":3446}}