{"ocr_results":[{"text":"神话没有再现，却传出了神话般的消息：“毛主席要接","box":[[239,166],[1050,167],[1050,201],[239,200]]},{"text":"见红卫兵！”","box":[[190,234],[374,231],[375,265],[190,268]]},{"text":"8月16日晚上，毛泽东就己同意在北京召开白万人规模","box":[[257,302],[1047,302],[1047,326],[257,326]]},{"text":"的“庆祝无产阶级文化大革命”群众大会，参加大会的主要","box":[[192,367],[1048,367],[1048,394],[192,394]]},{"text":"是来自北京和全国各地的青年学生。大会日期定在8月18","box":[[192,432],[1049,432],[1049,458],[192,458]]},{"text":"日，毛泽东表示将出席这次大会，接见北京的红卫兵，并要","box":[[193,495],[1050,495],[1050,525],[193,525]]},{"text":"求为他准备一套军装。","box":[[192,561],[500,561],[500,588],[192,588]]}],"dimensions":{"height":1754,"width":1241}}