{"ocr_results":[{"text":"相继汇集龙华镇。其中，上海卫生学校出动百余名学生肩扛木枪护卫","box":[[192,172],[1047,172],[1047,196],[192,196]]},{"text":"塔前。至晚上20时，塔前龙华路一带，护塔者、观望者云集万余人，","box":[[190,237],[1042,237],[1042,264],[190,264]]},{"text":"通道为之阻塞。午夜，未见扬言烧塔者动静，就留下部分人通宵守护。","box":[[192,304],[1041,304],[1041,328],[192,328]]},{"text":"28日，有人献策：在塔身上凌空悬挂巨幅政治标语作为“护身符”","box":[[249,368],[1043,368],[1043,395],[249,395]]},{"text":"以遏制毁塔。当天,在塔的南、北、西三面就出现3幅政治标语，从塔","box":[[195,434],[1047,434],[1047,457],[195,457]]},{"text":"顶直悬塔底，使七层古塔获得了有效的“护卫”，古塔方幸免于难。","box":[[193,498],[1013,498],[1013,522],[193,522]]},{"text":"9月14日，寺内珍藏的明神宗朱翊钧于万历二十九年（1601年)","box":[[247,562],[1044,561],[1044,588],[247,589]]},{"text":"救赐《藏经》718函5048卷，以及清同治年间自京师所领的“江浙所","box":[[192,629],[1047,629],[1047,653],[192,653]]},{"text":"罕有的释教中《藏经》数十部”均被当作废纸，作价每公斤0.12元","box":[[191,691],[1040,693],[1040,720],[191,718]]},{"text":"售给废品回收站。共重1763公斤（含其他纸品），售价仅211.56元。","box":[[192,755],[1026,757],[1026,784],[192,782]]},{"text":"《藏经》化作废品去，寺内空剩藏经板。","box":[[265,824],[737,824],[737,848],[265,848]]},{"text":"驰誉海内外的沪城八景之一的“龙华晚钟”，是一口珍贵的铜钟，","box":[[250,888],[1044,888],[1044,912],[250,912]]},{"text":"据说钟声悠扬，可传方圆十里。铜钟和寺内已被砸碎的范金十叶宝莲","box":[[191,954],[1049,954],[1049,977],[191,977]]},{"text":"毗卢遮那佛像，均于9月30日被用气焊切割成铜块后，作价每公斤3","box":[[192,1018],[1049,1018],[1049,1041],[192,1041]]},{"text":"元，售予废品回收站。被切割的铜钟重2574公斤，售得废铜价7722元","box":[[192,1082],[1040,1082],[1040,1109],[192,1109]]},{"text":"毗卢遮那铜佛碎块计重334.6公斤，得价1003.8元。600年金铭毁于","box":[[191,1148],[1047,1148],[1047,1172],[191,1172]]},{"text":"一旦。","box":[[187,1209],[261,1209],[261,1246],[187,1246]]},{"text":"古钟已毁，只能在流行的“南屏晚钟”歌声中，领略一点“龙","box":[[279,1277],[1049,1277],[1049,1304],[279,1304]]},{"text":"华晚钟”的风情。","box":[[191,1341],[402,1341],[402,1369],[191,1369]]},{"text":"24日这大，同样始建于汉朝的上海静安寺，好儿批红卫兵冲进","box":[[249,1408],[1049,1408],[1049,1432],[249,1432]]},{"text":"去，推翻供桌，打翻香炉，庙里十八罗汉塑像统统被戴上高帽子，静","box":[[193,1474],[1048,1474],[1048,1497],[193,1497]]},{"text":"安古寺前的千年沸井被填没，珍贵的真言宗密坛被捣毁，仅剩下几间","box":[[190,1536],[1048,1537],[1048,1564],[190,1563]]}],"dimensions":{"height":1754,"width":1241}}