{"ocr_results":[{"text":"胆地揭发上海市委的问题，北京的同学你们对上海市委有意见，","box":[[192,173],[1039,173],[1039,197],[192,197]]},{"text":"我们也表示欢迎。北京来的同学来上海后曾经对文化革命产生若","box":[[191,236],[1048,236],[1048,263],[191,263]]},{"text":"千问题，产生了不同意见，并产生了辩论，这个不同意见的辩论","box":[[191,302],[1048,301],[1048,328],[191,329]]},{"text":"是不可避免的，自然的，譬如，关于文斗武斗的问题，我们是赞","box":[[191,367],[1048,366],[1048,393],[191,394]]},{"text":"成文斗的……··.”","box":[[188,431],[393,421],[394,456],[190,466]]},{"text":"现场高喊：“要文斗！\"","box":[[250,495],[544,492],[544,524],[251,527]]},{"text":"曹荻秋：“这是符合毛泽东思想的，符合十六条的。最近，","box":[[255,561],[1028,560],[1028,588],[255,589]]},{"text":"林彪同志代表毛主席对这个问题有个专门讲话，同学们都看到","box":[[192,627],[1048,627],[1048,654],[192,654]]},{"text":"了。","box":[[190,690],[236,690],[236,724],[190,724]]},{"text":"林彪同志在讲话中特别强调不能动手打人，说这只能触其皮","box":[[254,757],[1047,757],[1047,781],[254,781]]},{"text":"肉，而不能触其灵魂，你把他人都搞得不能说话了，你们把人打","box":[[193,823],[1047,823],[1047,847],[193,847]]},{"text":"死了怎能斗臭？”","box":[[187,885],[423,880],[424,914],[187,919]]},{"text":"众呼：“坚决支持！\"","box":[[250,951],[516,948],[516,979],[251,982]]},{"text":"曹荻秋：“关于8月31日事件·…····8月31日上午北京一部","box":[[255,1015],[1050,1015],[1050,1044],[255,1044]]},{"text":"分人和上海一小部分人冲进上海市委，······竟打了上海市委的工","box":[[192,1081],[1050,1081],[1050,1108],[192,1108]]},{"text":"作人员。”","box":[[188,1145],[314,1143],[314,1175],[188,1177]]},{"text":"众呼：“对！要文斗！”","box":[[251,1211],[544,1209],[544,1239],[251,1241]]},{"text":"曹荻秋：“关于这一件事情，市委认为，由于一部分同学的","box":[[254,1276],[1049,1274],[1049,1304],[254,1306]]},{"text":"行动，市委是不赞成的，······但是有些人却到处发传单，说市委","box":[[192,1341],[1049,1341],[1049,1368],[192,1368]]},{"text":"打了北京同学三十儿个人，这全是胡说，单看今天的事情，有部","box":[[191,1407],[1049,1407],[1049,1434],[191,1434]]},{"text":"分同学冲进了市委，至今还有部分同学在市委机关里····","box":[[189,1470],[974,1465],[975,1499],[189,1504]]},{"text":"学生呼：“坚决反对市委放毒！”","box":[[254,1536],[670,1535],[670,1563],[254,1564]]}],"dimensions":{"height":1754,"width":1241}}