{"ocr_results":[{"text":"六十、出访亚非欧十四国","box":[[696,211],[1107,208],[1107,245],[696,247]]},{"text":"1537","box":[[1486,213],[1565,213],[1565,252],[1486,252]]},{"text":"容之一，就是积极支持亚洲、非洲、拉丁美洲的民族解放运动”。","box":[[198,322],[1603,322],[1603,365],[198,365]]},{"text":"因为“中国就是从帝国主义和殖民主义锁下解放出来的国家。","box":[[201,398],[1603,398],[1603,438],[201,438]]},{"text":"我们与亚洲、非洲、拉丁美洲各国人民有着共同的遭遇。因此我","box":[[200,476],[1606,476],[1606,512],[200,512]]},{"text":"们就必然互相同情、互相支持。中国是已经取得胜利的国家，有","box":[[199,551],[1605,551],[1605,591],[199,591]]},{"text":"义务支持那些正在取得胜利和将要取得胜利的国家”。①对于有","box":[[197,623],[1607,622],[1607,666],[197,667]]},{"text":"的记者提出的刁难性问题，周恩来坦诚友好地一一给以回答。","box":[[199,701],[1534,701],[1534,741],[199,741]]},{"text":"美国加利福尼亚报纸记者问：“我想了解你对肯尼迪②被杀","box":[[297,772],[1607,772],[1607,818],[297,818]]},{"text":"害有何反应？”周恩来回答：“肯尼迪总统的遇害是你们国家的内","box":[[198,852],[1603,851],[1603,890],[198,892]]},{"text":"部事情。当然，暗杀本身是卑鄙可耻的。你知道，我们共产党人","box":[[198,927],[1606,927],[1606,967],[198,967]]},{"text":"反对任何这类行为，尽管被暗杀的人是敌视我们新中国的。”③","box":[[194,999],[1546,990],[1546,1045],[194,1054]]},{"text":"美国《时代》杂志记者问：“你的政府为什么反对部分核禁","box":[[298,1078],[1605,1078],[1605,1118],[298,1118]]},{"text":"试条约？”④周恩来回答：“这样一个条约，表示三个大国要垄断","box":[[195,1149],[1608,1149],[1608,1195],[195,1195]]},{"text":"核武器，所以我们要反对。我们主张全面禁止和彻底销毁核武","box":[[199,1231],[1605,1231],[1605,1267],[199,1267]]},{"text":"器，制止核战争。因为发生一场核大战，对人类是个大灾难。既","box":[[197,1304],[1606,1304],[1606,1347],[197,1347]]},{"text":"然如此，世界各国都应该过问，应该有权来讨论如何全面禁止和","box":[[197,1380],[1606,1380],[1606,1420],[197,1420]]},{"text":"彻底销毁核武器、制止核战争的问题。世界上不论是大国还是小","box":[[196,1454],[1605,1455],[1605,1495],[196,1494]]},{"text":"国，强国还是弱国，在政治上应该一律平等。关系到全人类命运","box":[[199,1531],[1605,1530],[1605,1569],[199,1570]]},{"text":"的问题应该由大家来共同讨论，而不应该由少数国家垄断这种讨","box":[[200,1608],[1606,1608],[1606,1643],[200,1643]]},{"text":"论，甚至把有利于少数垄断者的决定强加给没有参加讨论的国","box":[[197,1683],[1604,1683],[1604,1723],[197,1723]]},{"text":"家。”他进一步揭露道：“这个部分禁止核试验条约签字以后，美","box":[[197,1758],[1605,1758],[1605,1798],[197,1798]]},{"text":"国就不断进行地下核试验。美国总统和政府官员不断声称，要继","box":[[200,1836],[1604,1836],[1604,1872],[200,1872]]},{"text":"续核试验、生产和储存核武器，把核武器交给它的盟国，不承担","box":[[196,1909],[1606,1909],[1606,1948],[196,1948]]},{"text":"不使用核武器的义务。”“这证明，三国条约的签订，并没有减少","box":[[195,1982],[1605,1981],[1605,2024],[195,2025]]},{"text":"①③","box":[[267,2142],[347,2142],[347,2183],[267,2183]]},{"text":"《周恩来外交文选》，中央文献出版社1990年5月版，第374、375、376","box":[[400,2146],[1609,2146],[1609,2178],[400,2178]]},{"text":"页。","box":[[193,2201],[252,2201],[252,2241],[193,2241]]},{"text":"②","box":[[268,2259],[303,2259],[303,2292],[268,2292]]},{"text":"1963年11月22日在争取连任总统的竞选旅途中遇刺身亡","box":[[347,2261],[1292,2261],[1292,2293],[347,2293]]},{"text":"④","box":[[269,2316],[307,2316],[307,2347],[269,2347]]},{"text":"指1963年8月5日美国、英国、苏联签订的《禁止在大气层、外层空间和水","box":[[345,2318],[1604,2318],[1604,2347],[345,2347]]},{"text":"下进行核试验条约》。","box":[[198,2374],[530,2374],[530,2406],[198,2406]]}],"dimensions":{"height":2681,"width":1816}}