{"ocr_results":[{"text":"第一章我親的文化大革命","box":[[460,89],[697,89],[697,109],[460,109]]},{"text":"主席和副主席？“插手軍隧”，是最榮臻等人政變篡","box":[[112,127],[696,127],[696,147],[112,147]]},{"text":"權後，指责别人最常見的事，還都作為犯罪行為上上線。","box":[[112,165],[694,165],[694,185],[112,185]]},{"text":"而且康生同志的上述批示，成了康生同志的“罪行”，白","box":[[112,203],[695,203],[695,223],[112,223]]},{"text":"黑字寫在中央下發的“康生“罪行’材料”裹。那，","box":[[111,241],[696,240],[696,260],[111,261]]},{"text":"榮臻就有權請康生同志“插手軍隧”？而且關於彭","box":[[111,279],[696,278],[696,299],[111,300]]},{"text":"德懷同志的問题，還可大言不惭地毛主席迫害彭德","box":[[113,318],[697,318],[697,338],[113,338]]},{"text":"懷，可在背地裹，他們参與的這些诬告勾當算什魔？那","box":[[112,355],[697,354],[697,374],[112,375]]},{"text":"還有皮對“文革”三道四。還有什本指责旁人“插","box":[[111,393],[697,392],[697,413],[111,414]]},{"text":"手軍隧”？","box":[[111,432],[211,430],[212,450],[112,453]]},{"text":"聂榮臻操偽保隧副“總勤務站”，打著“三軍無革","box":[[162,470],[696,468],[696,488],[162,490]]},{"text":"派”黑旗，隨便参舆揪门原北京軍區司令員杨勇、彭德","box":[[112,508],[697,508],[697,528],[112,528]]},{"text":"懷等軍像老幹部。他們搞“氣式”體，在夏日炎炎下，","box":[[113,547],[696,547],[696,566],[113,566]]},{"text":"把一些老同志體、折磨得满頭冒汗，汗珠不向地下滴。","box":[[111,584],[697,583],[697,604],[111,605]]},{"text":"可是，當他們篡權後，竟能大言不惭地诬造反派“迫害","box":[[112,623],[688,621],[688,641],[112,643]]},{"text":"老乾部，真不知天下還有羞耻二字。他們追害其他非科","box":[[112,660],[696,659],[696,680],[112,681]]},{"text":"委系統的軍内、外老同志的批门會，就不一一介绍了。","box":[[113,699],[663,699],[663,719],[113,719]]},{"text":"我要請問：有人不是張春橘同志是“福國殃民”","box":[[162,738],[696,736],[696,755],[162,757]]},{"text":"的“四人”、康生同志是“四人”一的，那，","box":[[112,775],[697,775],[697,795],[112,795]]},{"text":"榮臻把劉毅民蔻意陷彭德懷等老同志的匿名信送給了","box":[[112,814],[695,812],[695,832],[112,834]]},{"text":"康生同志；劉毅民背了黛組，私設迫害彭德等老同志","box":[[112,852],[697,851],[697,870],[112,871]]},{"text":"的黑“專案”，亚把“蕃查報告”送給了張春橘同志；最","box":[[112,890],[697,890],[697,910],[112,910]]},{"text":"榮臻操控的偽保陈副“總勤務站”同劉毅民勾結在一起，","box":[[113,929],[695,929],[695,949],[113,949]]},{"text":"利用康生同志在榮臻的信上的批示，當作“聖旨”，非","box":[[113,966],[697,966],[697,986],[113,986]]},{"text":"法關押了鞠芳和張伯恒同志，挑動武门，砸了所委，","box":[[111,1005],[697,1004],[697,1024],[111,1025]]},{"text":"把情報所搞痪長達三年之久（直到劉毅民篡奪了權為","box":[[111,1043],[697,1042],[697,1062],[111,1063]]},{"text":"止)。按照某些人立的“中央清查‘三種人’”的標，","box":[[111,1079],[697,1077],[697,1100],[111,1102]]},{"text":"-57-","box":[[666,1151],[701,1151],[701,1174],[666,1174]]}],"dimensions":{"height":1204,"width":809}}